sudoku/__init__.py
sudoku/_driver.py
sudoku/_show_grid.py
sudoku/_sudoku_generator.py
sudoku/_sudoku_solver.py
sudoku/_validty_check.py
sudokugame-1.1.4.dist-info/LICENSE
sudokugame-1.1.4.dist-info/METADATA
sudokugame-1.1.4.dist-info/WHEEL
sudokugame-1.1.4.dist-info/top_level.txt
sudokugame-1.1.4.dist-info/RECORD
