Metadata-Version: 2.1
Name: sudokugame
Version: 1.1.4
Summary: A Python package to generate sudoku
Author-email: Don Sabu <donsabu@protonmail.com>, Aneeta Jose <aneetajose@tutanota.com>
Project-URL: Source, https://github.com/don-sabu/sudoku
Keywords: sudoku
Requires-Python: >=3.7
License-File: LICENSE
